{
  "meta": {
    "generated_at": "2026-07-19T09:39:54Z",
    "refresh_seconds": 10,
    "source": "ACC Race Control live snapshots",
    "server_count": 5,
    "online_count": 5,
    "offline_count": 0,
    "total_players": 0,
    "warnings": []
  },
  "servers": [
    {
      "key": "1780300391",
      "name": "SPA",
      "track_key": "spa",
      "track_name": "Spa-Francorchamps",
      "online": true,
      "server_state": "online",
      "session_type": "Qualifying",
      "session_phase": "waiting for drivers",
      "session_remaining_minutes": 0.0,
      "players": 0,
      "source_updated_at": "2026-07-18T20:11:16.4607943Z"
    },
    {
      "key": "1780323950",
      "name": "ZOLDER",
      "track_key": "zolder",
      "track_name": "Zolder",
      "online": true,
      "server_state": "online",
      "session_type": "Practice",
      "session_phase": "waiting for drivers",
      "session_remaining_minutes": 2.0,
      "players": 0,
      "source_updated_at": "2026-07-19T07:39:14.2456266Z"
    },
    {
      "key": "1781810063",
      "name": "Brands Hatch",
      "track_key": "brands_hatch",
      "track_name": "Brands Hatch",
      "online": true,
      "server_state": "online",
      "session_type": "Qualifying",
      "session_phase": "waiting for drivers",
      "session_remaining_minutes": 25.0,
      "players": 0,
      "source_updated_at": "2026-07-18T21:41:11.0220908Z"
    },
    {
      "key": "1782666925",
      "name": "MONZA",
      "track_key": "monza",
      "track_name": "Monza",
      "online": true,
      "server_state": "online",
      "session_type": "Qualifying",
      "session_phase": "waiting for drivers",
      "session_remaining_minutes": 30.0,
      "players": 0,
      "source_updated_at": "2026-07-19T07:20:29.8751683Z"
    },
    {
      "key": "1783207500",
      "name": "Nordschleife 24",
      "track_key": "nurburgring_24h",
      "track_name": "Nürburgring 24h",
      "online": true,
      "server_state": "online",
      "session_type": "Qualifying",
      "session_phase": "waiting for drivers",
      "session_remaining_minutes": 30.0,
      "players": 0,
      "source_updated_at": "2026-07-19T07:45:34.1482105Z"
    }
  ]
}